setup.py
genomfart/__init__.py
genomfart.egg-info/PKG-INFO
genomfart.egg-info/SOURCES.txt
genomfart.egg-info/dependency_links.txt
genomfart.egg-info/top_level.txt
genomfart/data/__init__.py
genomfart/data/data_constants.py
genomfart/data/test_gff.gff
genomfart/parsers/AGPmap.py
genomfart/parsers/SNPdata.py
genomfart/parsers/__init__.py
genomfart/parsers/gff.py
genomfart/parsers/vcf.py
genomfart/popgen/__init__.py
genomfart/popgen/genetic_relationship.py
genomfart/stats/__init__.py
genomfart/stats/pgm.py
genomfart/stats/slice_sampler.py
genomfart/test/__init__.py
genomfart/test/parsers/__init__.py
genomfart/test/parsers/gffTest.py
genomfart/test/parsers/vcfTest.py
genomfart/test/utils/__init__.py
genomfart/test/utils/bigDataFrameTest.py
genomfart/test/utils/version_mapper_test.py
genomfart/utils/__init__.py
genomfart/utils/bigDataFrame.py
genomfart/utils/caching.py
genomfart/utils/genomeAnnotationGraph.py
genomfart/utils/polymorphism_formatter.py
genomfart/utils/snp_projector.py
genomfart/utils/version_mapper.py
genomfart/utils/scripts/__init__.py
genomfart/utils/scripts/shuffle_plink_phenotype_within_family.py